umbrix_mcp/__init__.py
umbrix_mcp/server.py
umbrix_mcp-0.2.0.dist-info/METADATA
umbrix_mcp-0.2.0.dist-info/WHEEL
umbrix_mcp-0.2.0.dist-info/entry_points.txt
umbrix_mcp-0.2.0.dist-info/licenses/LICENSE
umbrix_mcp-0.2.0.dist-info/RECORD
