Metadata-Version: 2.4
Name: umbrix-mcp
Version: 0.2.0
Summary: MCP server for Umbrix CTI platform - AI-powered threat intelligence
Project-URL: Homepage, https://umbrix.dev
Project-URL: Documentation, https://umbrix.dev/docs
Project-URL: Repository, https://github.com/umbrix/umbrix-mcp
Author-email: Umbrix Team <support@umbrix.dev>
License: MIT
License-File: LICENSE
Keywords: ai,claude,cti,mcp,security,threat-intelligence
Classifier: Development Status :: 4 - Beta
Classifier: Intended Audience :: Developers
Classifier: License :: OSI Approved :: MIT License
Classifier: Programming Language :: Python :: 3
Classifier: Programming Language :: Python :: 3.10
Classifier: Programming Language :: Python :: 3.11
Classifier: Programming Language :: Python :: 3.12
Requires-Python: >=3.10
Requires-Dist: httpx>=0.27.0
Requires-Dist: mcp>=1.9.4
Requires-Dist: pydantic>=2.0.0
Requires-Dist: python-dotenv>=1.0.0
Provides-Extra: dev
Requires-Dist: black>=23.0.0; extra == 'dev'
Requires-Dist: pylint>=3.3.7; extra == 'dev'
Requires-Dist: pytest-asyncio>=0.21.0; extra == 'dev'
Requires-Dist: pytest>=7.0.0; extra == 'dev'
Requires-Dist: ruff>=0.1.0; extra == 'dev'
